sploitscan/__init__.py
sploitscan/__main__.py
sploitscan/ai.py
sploitscan/cli.py
sploitscan/compose.py
sploitscan/config.json
sploitscan/config.py
sploitscan/constants.py
sploitscan/display.py
sploitscan/metrics.py
sploitscan/paths.py
sploitscan/repo.py
sploitscan/search.py
sploitscan/sploitscan.py
sploitscan/utils.py
sploitscan/ai_providers/deepseek_provider.py
sploitscan/ai_providers/google_provider.py
sploitscan/ai_providers/grok_provider.py
sploitscan/ai_providers/openai_provider.py
sploitscan/exporters/csv_exporter.py
sploitscan/exporters/html_exporter.py
sploitscan/exporters/json_exporter.py
sploitscan/fetchers/cisa.py
sploitscan/fetchers/common.py
sploitscan/fetchers/cve.py
sploitscan/fetchers/epss.py
sploitscan/fetchers/exploitdb.py
sploitscan/fetchers/github_poc.py
sploitscan/fetchers/hackerone.py
sploitscan/fetchers/metasploit.py
sploitscan/fetchers/nuclei.py
sploitscan/fetchers/vulncheck.py
sploitscan/importers/__init__.py
sploitscan/templates/report_template.html
sploitscan-0.14.2.dist-info/LICENSE
sploitscan-0.14.2.dist-info/METADATA
sploitscan-0.14.2.dist-info/WHEEL
sploitscan-0.14.2.dist-info/entry_points.txt
sploitscan-0.14.2.dist-info/top_level.txt
sploitscan-0.14.2.dist-info/RECORD
