Metadata-Version: 2.1
Name: sploitscan
Version: 0.14.2
Summary: SploitScan is a cybersecurity utility designed to provide detailed information on vulnerabilities and associated exploits.
Author-email: Alexander Hagenah <ah@primepage.de>
License: GNU GENERAL PUBLIC LICENSE
Project-URL: homepage, https://github.com/xaitax/SploitScan
Project-URL: repository, https://github.com/xaitax/SploitScan
Project-URL: documentation, https://github.com/xaitax/SploitScan#readme
Project-URL: changelog, https://github.com/xaitax/SploitScan
Requires-Python: >=3.8
License-File: LICENSE
Requires-Dist: requests==2.32.5
Requires-Dist: jinja2==3.1.6
Requires-Dist: openai==2.2.0
Requires-Dist: google-genai==1.41.0
Requires-Dist: GitPython==3.1.45
Requires-Dist: tqdm==4.67.1
